MANIFEST.in
setup.cfg
setup.py
docs/Makefile
docs/conf.py
docs/index.rst
docs/usage.rst
snakefight/__init__.py
snakefight/command.py
snakefight/util.py
snakefight.egg-info/PKG-INFO
snakefight.egg-info/SOURCES.txt
snakefight.egg-info/dependency_links.txt
snakefight.egg-info/entry_points.txt
snakefight.egg-info/top_level.txt
snakefight.egg-info/zip-safe
snakefight/war_template/WEB-INF/web.xml_tmpl