Metadata-Version: 1.0
Name: snakefight
Version: 0.5
Summary: Assembles WAR files from Python (Jython) WSGI applications
Home-page: http://pypi.python.org/pypi/snakefight
Author: Philip Jenvey
Author-email: pjenvey@underboss.org
License: BSD
Keywords: jython war
Platform: UNKNOWN
Classifier: Intended Audience :: Developers
Classifier: License :: OSI Approved :: BSD License
Classifier: Programming Language :: Python
Classifier: Programming Language :: Python :: Implementation :: Jython
Classifier: Topic :: Internet :: WWW/HTTP
Classifier: Topic :: Internet :: WWW/HTTP :: Dynamic Content
Classifier: Topic :: Internet :: WWW/HTTP :: WSGI
